LICENSE
README
setup.cfg
setup.py
cube_async_w_kafka/ConfigManager.py
cube_async_w_kafka/NetManager.py
cube_async_w_kafka/__init__.py
cube_async_w_kafka.egg-info/PKG-INFO
cube_async_w_kafka.egg-info/SOURCES.txt
cube_async_w_kafka.egg-info/dependency_links.txt
cube_async_w_kafka.egg-info/requires.txt
cube_async_w_kafka.egg-info/top_level.txt
cube_async_w_kafka/Checkers/NetworkPlane_Checker.py
cube_async_w_kafka/Checkers/Provider_Checker.py
cube_async_w_kafka/Checkers/__init__.py
cube_async_w_kafka/Networkplane/A_Network_Plane.py
cube_async_w_kafka/Networkplane/Exceptions.py
cube_async_w_kafka/Networkplane/Network_Plane.py
cube_async_w_kafka/Networkplane/Task.py
cube_async_w_kafka/Networkplane/__init__.py