Metadata-Version: 2.1
Name: cube-async-w-kafka
Version: 0.8
Summary: Kafka service provider for Outbound traffic in asynchronous mode
Home-page: https://github.com/QuanticData
Author: Abdallah Ben Hamida
Author-email: noemail@gmail.com
License: MIT
Keywords: dict,python,kafka
Platform: UNKNOWN
Classifier: Development Status :: 5 - Production/Stable
Classifier: Intended Audience :: Developers
Classifier: Topic :: Software Development :: Build Tools
Classifier: License :: OSI Approved :: MIT License
Classifier: Programming Language :: Python :: 3
License-File: LICENSE
